qiskit_machine_learning/VERSION.txt
qiskit_machine_learning/__init__.py
qiskit_machine_learning/algorithm_job.py
qiskit_machine_learning/algorithm_result.py
qiskit_machine_learning/exceptions.py
qiskit_machine_learning/optionals.py
qiskit_machine_learning/py.typed
qiskit_machine_learning/variational_algorithm.py
qiskit_machine_learning/version.py
qiskit_machine_learning/algorithms/__init__.py
qiskit_machine_learning/algorithms/objective_functions.py
qiskit_machine_learning/algorithms/serializable_model.py
qiskit_machine_learning/algorithms/trainable_model.py
qiskit_machine_learning/algorithms/classifiers/__init__.py
qiskit_machine_learning/algorithms/classifiers/neural_network_classifier.py
qiskit_machine_learning/algorithms/classifiers/pegasos_qsvc.py
qiskit_machine_learning/algorithms/classifiers/qsvc.py
qiskit_machine_learning/algorithms/classifiers/vqc.py
qiskit_machine_learning/algorithms/inference/__init__.py
qiskit_machine_learning/algorithms/inference/qbayesian.py
qiskit_machine_learning/algorithms/regressors/__init__.py
qiskit_machine_learning/algorithms/regressors/neural_network_regressor.py
qiskit_machine_learning/algorithms/regressors/qsvr.py
qiskit_machine_learning/algorithms/regressors/vqr.py
qiskit_machine_learning/circuit/__init__.py
qiskit_machine_learning/circuit/library/__init__.py
qiskit_machine_learning/circuit/library/qnn_circuit.py
qiskit_machine_learning/circuit/library/raw_feature_vector.py
qiskit_machine_learning/connectors/__init__.py
qiskit_machine_learning/connectors/torch_connector.py
qiskit_machine_learning/datasets/__init__.py
qiskit_machine_learning/datasets/ad_hoc.py
qiskit_machine_learning/gradients/__init__.py
qiskit_machine_learning/gradients/qfi.py
qiskit_machine_learning/gradients/qfi_result.py
qiskit_machine_learning/gradients/utils.py
qiskit_machine_learning/gradients/base/__init__.py
qiskit_machine_learning/gradients/base/base_estimator_gradient.py
qiskit_machine_learning/gradients/base/base_qgt.py
qiskit_machine_learning-0.8.0.dist-info/LICENSE.txt
qiskit_machine_learning-0.8.0.dist-info/METADATA
qiskit_machine_learning-0.8.0.dist-info/WHEEL
qiskit_machine_learning-0.8.0.dist-info/top_level.txt
qiskit_machine_learning-0.8.0.dist-info/RECORD
