Metadata-Version: 2.1
Name: qiskit-machine-learning
Version: 0.8.0
Summary: Qiskit Machine Learning: A library of quantum computing machine learning experiments
Home-page: https://github.com/qiskit-community/qiskit-machine-learning
Author: Qiskit Machine Learning Development Team
Author-email: qiskit@us.ibm.com
License: Apache-2.0
Project-URL: Bug Tracker, https://github.com/qiskit-community/qiskit-machine-learning/issues
Project-URL: Documentation, https://qiskit-community.github.io/qiskit-machine-learning/
Project-URL: Source Code, https://github.com/qiskit-community/qiskit-machine-learning
Keywords: qiskit sdk quantum machine learning ml
Classifier: Environment :: Console
Classifier: License :: OSI Approved :: Apache Software License
Classifier: Intended Audience :: Developers
Classifier: Intended Audience :: Science/Research
Classifier: Operating System :: Microsoft :: Windows
Classifier: Operating System :: MacOS
Classifier: Operating System :: POSIX :: Linux
Classifier: Programming Language :: Python :: 3 :: Only
Classifier: Programming Language :: Python :: 3.9
Classifier: Programming Language :: Python :: 3.10
Classifier: Programming Language :: Python :: 3.11
Classifier: Programming Language :: Python :: 3.12
Classifier: Topic :: Scientific/Engineering
Requires-Python: >=3.9
License-File: LICENSE.txt
Requires-Dist: qiskit>=1.0
Requires-Dist: scipy>=1.4
Requires-Dist: numpy>=1.17
Requires-Dist: psutil>=5
Requires-Dist: scikit-learn>=1.2.0
Requires-Dist: fastdtw
Requires-Dist: setuptools>=40.1.0
Requires-Dist: dill>=0.3.4
Provides-Extra: sparse
Requires-Dist: sparse; extra == "sparse"
Provides-Extra: torch
Requires-Dist: torch; extra == "torch"
